discord_compressor/__init__.py
discord_compressor/cli.py
discord_compressor/file_compressor.py
discord_file_compressor-0.1.5.data/scripts/post_install.py
discord_file_compressor-0.1.5.dist-info/LICENSE
discord_file_compressor-0.1.5.dist-info/METADATA
discord_file_compressor-0.1.5.dist-info/WHEEL
discord_file_compressor-0.1.5.dist-info/entry_points.txt
discord_file_compressor-0.1.5.dist-info/top_level.txt
discord_file_compressor-0.1.5.dist-info/RECORD
