Metadata-Version: 2.1
Name: discord-file-compressor
Version: 0.1.5
Summary: A tool to compress files for Discord's 10MB limit
Home-page: https://github.com/Abdude790/discord-file-compressor
Author: Abdude790
Author-email: your.email@example.com
Classifier: Programming Language :: Python :: 3
Classifier: License :: OSI Approved :: MIT License
Classifier: Operating System :: OS Independent
Requires-Python: >=3.7
License-File: LICENSE
Requires-Dist: Pillow >=9.0.0
Requires-Dist: pyperclip >=1.8.2
Requires-Dist: plyer >=2.1.0
